baltimorestrings/__init__.py
baltimorestrings/venver/__init__.py
baltimorestrings/venver/_venver.py
baltimorestrings.venver-0.1.3.dist-info/METADATA
baltimorestrings.venver-0.1.3.dist-info/WHEEL
baltimorestrings.venver-0.1.3.dist-info/entry_points.txt
baltimorestrings.venver-0.1.3.dist-info/top_level.txt
baltimorestrings.venver-0.1.3.dist-info/RECORD
