Metadata-Version: 2.1
Name: baltimorestrings.venver
Version: 0.1.3
Summary: venver
Author: baltimorestrings
License: LICENSE
Project-URL: homepage, https://github.com/baltimorestrings/venver
Classifier: Development Status :: 5 - Production/Stable
Classifier: Programming Language :: Python :: 3.11
Requires-Python: >=3.8
Requires-Dist: tomli
